AIS/__init__.py
AIS/ais.py
AIS/exceptions.py
AIS/helpers.py
AIS/pdf.py
AIS/empty_signer/EmptySigner.class
AIS/empty_signer/EmptySigner.java
AIS/empty_signer/Makefile
AIS/empty_signer/README.md
AIS/empty_signer/vendor/LICENSE.md
AIS/empty_signer/vendor/README.md
AIS/empty_signer/vendor/itextpdf-5.5.9.jar
AIS.py-0.2.2.dist-info/DESCRIPTION.rst
AIS.py-0.2.2.dist-info/METADATA
AIS.py-0.2.2.dist-info/RECORD
AIS.py-0.2.2.dist-info/WHEEL
AIS.py-0.2.2.dist-info/metadata.json
AIS.py-0.2.2.dist-info/top_level.txt
